setup.py
ndd_panda.egg-info/PKG-INFO
ndd_panda.egg-info/SOURCES.txt
ndd_panda.egg-info/dependency_links.txt
ndd_panda.egg-info/requires.txt
ndd_panda.egg-info/top_level.txt
panda/__init__.py
panda/default_config.py
panda/bench/__init__.py
panda/bench/discriminibility.py
panda/bench/metrics.py
panda/bench/transforms.py
panda/bench/utilities.py
panda/methods/__init__.py
panda/methods/bad_chans.py
panda/methods/denoise.py
panda/methods/derivatives.py
panda/methods/interpolation.py
panda/methods/misc.py
panda/methods/pcp.py
panda/methods/signals.py
panda/methods/viz.py
panda/scripts/panda_pipeline
panda/utils/__init__.py
panda/utils/bids_s3.py
panda/utils/system.py