Metadata-Version: 1.0
Name: ndd-panda
Version: 1.11
Summary: Neuro Data Design EEG Preprocessing Pipeline
Home-page: https://github.com/NeuroDataDesign/orange-panda
Author: Ryan Marren and Nitin Kumar
Author-email: rmarren1@jhu.edu, nkumarcc@gmail.com
License: UNKNOWN
Keywords: eeg,pipeline
Platform: UNKNOWN
